typed_macro/__init__.py
typed_macro/cli.py
typed_macro/constants.py
typed_macro/file_writers.py
typed_macro/inline_codegen.py
typed_macro/macro_codegen.py
typed_macro/py.typed
typed_macro/util.py
typed_macro-0.1.16.dist-info/METADATA
typed_macro-0.1.16.dist-info/WHEEL
typed_macro-0.1.16.dist-info/entry_points.txt
typed_macro-0.1.16.dist-info/top_level.txt
typed_macro-0.1.16.dist-info/RECORD
