Metadata-Version: 2.1
Name: typed-macro
Version: 0.1.16
Summary: Use procedural macros with type annotations in Python
Requires-Python: >=3.12
Requires-Dist: executing>=2.1.0
Requires-Dist: gitpython>=3.1.43
Requires-Dist: libcst>=1.5.1
Requires-Dist: typer>=0.15.1
